enum_utils/__init__.py
enum_utils/enum_utils.py
shipmnts_alex_enum-0.4.dist-info/LICENSE
shipmnts_alex_enum-0.4.dist-info/METADATA
shipmnts_alex_enum-0.4.dist-info/WHEEL
shipmnts_alex_enum-0.4.dist-info/top_level.txt
shipmnts_alex_enum-0.4.dist-info/RECORD
