Metadata-Version: 2.1
Name: shipmnts-alex-enum
Version: 0.4
Summary: An Enum (currency, freight terms, and weight UOM) utility package
Home-page: https://github.com/charmiShipmnts/shipmnts-alex-enum
Author: Charmi Chokshi
Author-email: charmi@shipmnts.com
License: UNKNOWN
Platform: UNKNOWN
Classifier: Programming Language :: Python :: 3
Classifier: License :: OSI Approved :: MIT License
Classifier: Operating System :: OS Independent
